kclient/__init__.py
kclient/api_client.py
kclient/configuration.py
kclient/rest.py
kclient/api/__init__.py
kclient/api/inference_api.py
kclient/api/ml_model_api.py
kclient/api/serving_api.py
kclient/models/__init__.py
kclient/models/application_application_model_version.py
kclient/models/application_project_serving_job.py
kclient/models/application_project_serving_job_output.py
kclient/models/dealerclient_resource_limit.py
kclient/models/inference_run_serving_request.py
kclient/models/mlapp_autoscale.py
kclient/models/mlapp_dataset_fs_source.py
kclient/models/mlapp_dataset_source.py
kclient/models/mlapp_env.py
kclient/models/mlapp_git_repo_volume_source.py
kclient/models/mlapp_images.py
kclient/models/mlapp_model_source.py
kclient/models/mlapp_persistent_storage.py
kclient/models/mlapp_port.py
kclient/models/mlapp_resource_accelerators.py
kclient/models/mlapp_resource_request.py
kclient/models/mlapp_s3_bucket_source.py
kclient/models/mlapp_serving.py
kclient/models/mlapp_serving_response_param.py
kclient/models/mlapp_serving_spec.py
kclient/models/mlapp_serving_spec_options.py
kclient/models/mlapp_serving_spec_param.py
kclient/models/mlapp_serving_spec_param_value.py
kclient/models/mlapp_universal_serving.py
kclient/models/mlapp_volume.py
kclient/models/mlapp_volume_mount.py
kclient/models/models_application_model.py
kclient/models/models_application_model_config.py
kclient/models/models_application_model_config_serving.py
kclient/models/models_application_model_source.py
kclient/models/models_application_model_version_stored_data.py
kclient/models/models_arbitrary.py
kclient/models/models_catalog_item_obj.py
kclient/models/models_forked_item.py
kclient/models/models_inference_version.py
kclient/models/models_serving.py
kclient/models/models_task_form_element.py
kclient/models/models_task_form_element_stream_extended.py
kclient/models/models_task_form_element_value.py
kclient/models/models_user.py
kclient/models/v1_empty_dir_volume_source.py
python_kclient-1.0.0.dist-info/METADATA
python_kclient-1.0.0.dist-info/WHEEL
python_kclient-1.0.0.dist-info/top_level.txt
python_kclient-1.0.0.dist-info/RECORD
